demerzel/__init__.py
demerzel/app.py
demerzel/config.py
demerzel/consumer.py
demerzel/enums.py
demerzel/producer.py
demerzel/queues.py
demerzel/scheduler.py
demerzel/task.py
demerzel-0.2.1.dist-info/LICENSE
demerzel-0.2.1.dist-info/METADATA
demerzel-0.2.1.dist-info/WHEEL
demerzel-0.2.1.dist-info/top_level.txt
demerzel-0.2.1.dist-info/RECORD
